ark_algebra_py-0.2.1.dist-info/METADATA
ark_algebra_py-0.2.1.dist-info/WHEEL
ark_algebra_py/__init__.py
ark_algebra_py/ark_algebra_py.abi3.so
ark_algebra_py-0.2.1.dist-info/RECORD
